font_manrope/__init__.py
font_manrope/files/Manrope-Bold.ttf
font_manrope/files/Manrope-ExtraBold.ttf
font_manrope/files/Manrope-ExtraLight.ttf
font_manrope/files/Manrope-Light.ttf
font_manrope/files/Manrope-Medium.ttf
font_manrope/files/Manrope-Regular.ttf
font_manrope/files/Manrope-SemiBold.ttf
font_manrope/files/Manrope-VariableFont_wght.ttf
font_manrope/files/OFL.txt
font_manrope-0.0.2.dist-info/METADATA
font_manrope-0.0.2.dist-info/WHEEL
font_manrope-0.0.2.dist-info/entry_points.txt
font_manrope-0.0.2.dist-info/top_level.txt
font_manrope-0.0.2.dist-info/RECORD
